CHANGELOG.txt
LICENSE.txt
MANIFEST.in
README.txt
ez_setup.py
setup.cfg
setup.py
FormBuild.egg-info/PKG-INFO
FormBuild.egg-info/SOURCES.txt
FormBuild.egg-info/dependency_links.txt
FormBuild.egg-info/entry_points.txt
FormBuild.egg-info/not-zip-safe
FormBuild.egg-info/requires.txt
FormBuild.egg-info/top_level.txt
doc/Makefile
doc/index.txt
doc/source/api.rst
doc/source/conf.py
doc/source/form1.png
doc/source/index.rst
doc/source/manual.rst
example/README.txt
example/census.py
example/common.py
example/common.pyc
formbuild/__init__.py
test/README.txt
test/doc.py
test/pylons_test.py