Metadata-Version: 1.0
Name: FormBuild
Version: 4.0.0
Summary: Build HTML forms quickly and easily. (Pre-release not ready for broad use, please use 0.3.x).
Home-page: http://jimmyg.org/work/code/formbuild/index.html
Author: James Gardner
Author-email: UNKNOWN
License: MIT
Platform: UNKNOWN
Classifier: Development Status :: 4 - Beta
Classifier: License :: OSI Approved :: MIT License
Classifier: Programming Language :: Python :: 2
Classifier: Topic :: Software Development :: Libraries :: Python Modules
Classifier: Environment :: Web Environment
